<?xml version="1.0" encoding="UTF-8"?>
<objects serializationModel="Studio.01.10.00">
    <object class="AudioFile" id="{66e009d9-e0e4-4b32-9993-2370edeff69a}">
        <property name="assetPath">
            <value>Stems/Bass/Bass_06.wav</value>
        </property>
        <property name="isStreaming">
            <value>true</value>
        </property>
        <property name="frequencyInKHz">
            <value>48</value>
        </property>
        <property name="channelCount">
            <value>2</value>
        </property>
        <property name="length">
            <value>14.769229166666667</value>
        </property>
        <relationship name="masterAssetFolder">
            <destination>{3ae6facf-14b1-4490-80e6-e747faad5da8}</destination>
        </relationship>
    </object>
</objects>
