<?xml version="1.0" encoding="UTF-8"?>
<objects serializationModel="Studio.02.00.00">
	<object class="AudioFile" id="{b26f8297-4ce1-4508-a19d-a73768a28e88}">
		<property name="assetPath">
			<value>Ambient/sci-fi_electric_pulse_power_down/sci-fi_electric_pulse_power_down_02.wav</value>
		</property>
		<property name="frequencyInKHz">
			<value>48</value>
		</property>
		<property name="channelCount">
			<value>2</value>
		</property>
		<property name="length">
			<value>5</value>
		</property>
		<relationship name="masterAssetFolder">
			<destination>{3ae6facf-14b1-4490-80e6-e747faad5da8}</destination>
		</relationship>
	</object>
</objects>
